ovos_plugin_mpv/__init__.py
ovos_plugin_mpv/version.py
ovos_audio_plugin_mpv-0.2.1.dist-info/LICENSE
ovos_audio_plugin_mpv-0.2.1.dist-info/METADATA
ovos_audio_plugin_mpv-0.2.1.dist-info/WHEEL
ovos_audio_plugin_mpv-0.2.1.dist-info/entry_points.txt
ovos_audio_plugin_mpv-0.2.1.dist-info/top_level.txt
ovos_audio_plugin_mpv-0.2.1.dist-info/RECORD
