Metadata-Version: 2.1
Name: ovos-audio-plugin-mpv
Version: 0.2.1
Summary: mpv plugin for ovos
Home-page: https://github.com/OpenVoiceOS/ovos-audio-plugin-mpv
Author: JarbasAi
Author-email: jarbasai@mailfence.com
License: Apache-2.0
Keywords: ovos audio plugin
Platform: UNKNOWN
Requires-Dist: ovos-plugin-manager>=0.0.26a29
Requires-Dist: python-mpv-jsonipc
